socialhub/__init__.py
socialhub/socialhub.py
socialhub-1.1.0.dist-info/METADATA
socialhub-1.1.0.dist-info/WHEEL
socialhub-1.1.0.dist-info/top_level.txt
socialhub-1.1.0.dist-info/zip-safe
socialhub-1.1.0.dist-info/RECORD
