Metadata-Version: 2.1
Name: socialhub
Version: 1.1.0
Summary: API client for socialhub.io
Home-page: https://github.com/uberspace/socialhub
Author: uberspace.de
Author-email: hallo@uberspace.de
Classifier: Development Status :: 4 - Beta
Classifier: Intended Audience :: Developers
Classifier: Intended Audience :: Customer Service
Classifier: Intended Audience :: Information Technology
Classifier: Natural Language :: English
Classifier: Programming Language :: Python :: 3 :: Only
Classifier: Programming Language :: Python :: 3.6
Classifier: Programming Language :: Python :: 3.7
Classifier: Programming Language :: Python :: 3.8
Classifier: Topic :: Software Development :: Libraries :: Python Modules
Requires-Dist: requests
Requires-Dist: dataclasses
